bronkhorstControlbm31/__init__.py
bronkhorstControlbm31/bronkhorst.py
bronkhorstControlbm31/bronkhorstClient.py
bronkhorstControlbm31/bronkhorstGui.py
bronkhorstControlbm31/bronkhorstServer.py
bronkhorstControlbm31/plotters.py
bronkhorstcontrolbm31-1.4.0.dist-info/licenses/LICENSE.md
bronkhorstcontrolbm31-1.4.0.dist-info/METADATA
bronkhorstcontrolbm31-1.4.0.dist-info/WHEEL
bronkhorstcontrolbm31-1.4.0.dist-info/entry_points.txt
bronkhorstcontrolbm31-1.4.0.dist-info/top_level.txt
bronkhorstcontrolbm31-1.4.0.dist-info/RECORD
