Metadata-Version: 2.4
Name: bronkhorstControlbm31
Version: 1.4.0
Summary: tools for communicating with Bronkhorst MFCs with the API for BM31
Author-email: "Kenneth P. Marshall" <kenneth.marshall@esrf.fr>
Maintainer-email: "Kenneth P. Marshall" <kenneth.marshall@esrf.fr>
License-Expression: GPL-3.0
Project-URL: repository, https://github.com/msujas/bronkhorstControl
Keywords: Bronkhorst,MFCs
Classifier: Development Status :: 4 - Beta
Classifier: Programming Language :: Python :: 3.12
Requires-Python: >=3.10
License-File: LICENSE.md
Requires-Dist: bronkhorst-propar
Requires-Dist: pandas
Requires-Dist: matplotlib
Requires-Dist: pyqt6
Dynamic: license-file
